{
  "title": "Propositional and Predicate Calculus: 2.4 Logical Equivalence",
  "post-filename": "logical-equivalence.html",
  "assets-file-directory-name": "logical-equivalence",
  "description": "Beau Carlborg's Website",
  "reading-title": "Propositional and Predicate Calculus: 2.4 Logical Equivalence",
  "reading-author": "Derek Goldrei",
  "reading-published-date": "2005",
  "reading-url": "",
  "date-read-by-me": "March 15, 2026",
  "date-last-updated": "2026/03/15",
  "post-order": 7,
  "author": "Beau Carlborg",
  "type": "Reading"
}
